zer0poc/__init__.py
zer0poc/exploit.py
zer0poc/logging.py
zer0poc/ssrf.py
zer0poc/utils.py
zer0poc-0.1.dist-info/LICENSE
zer0poc-0.1.dist-info/METADATA
zer0poc-0.1.dist-info/WHEEL
zer0poc-0.1.dist-info/top_level.txt
zer0poc-0.1.dist-info/RECORD
