Metadata-Version: 2.1
Name: zer0poc
Version: 0.1
Summary: PoC generater thats fast and pretty for your vulnerabilty.
Home-page: https://github.com/retr0reg/zer00poc
Author: 0reg
Author-email: 0reg@0reg.dev
License: MIT
License-File: LICENSE
Requires-Dist: Flask ==3.0.2
Requires-Dist: Requests ==2.31.0
